README.md
setup.py
pulumi_rockset/__init__.py
pulumi_rockset/_inputs.py
pulumi_rockset/_utilities.py
pulumi_rockset/alias.py
pulumi_rockset/api_key.py
pulumi_rockset/collection.py
pulumi_rockset/collection_mount.py
pulumi_rockset/dynamodb_collection.py
pulumi_rockset/dynamodb_integration.py
pulumi_rockset/gcs_collection.py
pulumi_rockset/gcs_integration.py
pulumi_rockset/get_account.py
pulumi_rockset/get_query_lambda_tag.py
pulumi_rockset/get_user.py
pulumi_rockset/get_virtual_instance.py
pulumi_rockset/get_workspace.py
pulumi_rockset/kafka_collection.py
pulumi_rockset/kafka_integration.py
pulumi_rockset/kinesis_collection.py
pulumi_rockset/kinesis_integration.py
pulumi_rockset/mongodb_collection.py
pulumi_rockset/mongodb_integration.py
pulumi_rockset/outputs.py
pulumi_rockset/provider.py
pulumi_rockset/pulumi-plugin.json
pulumi_rockset/py.typed
pulumi_rockset/query_lambda.py
pulumi_rockset/query_lambda_tag.py
pulumi_rockset/role.py
pulumi_rockset/s3_collection.py
pulumi_rockset/s3_integration.py
pulumi_rockset/user.py
pulumi_rockset/view.py
pulumi_rockset/virtual_instance.py
pulumi_rockset/workspace.py
pulumi_rockset.egg-info/PKG-INFO
pulumi_rockset.egg-info/SOURCES.txt
pulumi_rockset.egg-info/dependency_links.txt
pulumi_rockset.egg-info/not-zip-safe
pulumi_rockset.egg-info/requires.txt
pulumi_rockset.egg-info/top_level.txt
pulumi_rockset/config/__init__.py
pulumi_rockset/config/vars.py