Metadata-Version: 2.1
Name: pulumi-rockset
Version: 0.0.1a1702081582
Summary: A Pulumi package for creating and managing rockset cloud resources.
Home-page: https://www.pulumi.com
License: Apache-2.0
Project-URL: Repository, https://github.com/ddn0/pulumi-rockset
Keywords: pulumi rockset category/cloud
Requires-Python: >=3.7
